Workbook
Name Slicer_Category: #N/A
Name Slicer_CustomerTier: #N/A
Name Slicer_Region: #N/A

Sheet Orders
A1: OrderID | B1: CustomerID | C1: ProductID | D1: Quantity | E1: OrderDate | F1: Region | G1: Discount | H1: Status | I1: CleanRegion | J1: CleanStatus
A2: 1001 | B2: C001 | C2: P101 | D2: 2 | E2: 45296 | F2: East | G2: 0.1 | H2: Delivered | I2: =PROPER(tbl_Orders[[#This Row],[Region]]) -> East | J2: =PROPER(tbl_Orders[[#This Row],[Status]]) -> Delivered
A3: 1002 | B3: C002 | C3: P102 | D3: 1 | E3: 45298 | F3: West | G3: 0 | H3: Cancelled | I3: =PROPER(tbl_Orders[[#This Row],[Region]]) -> West | J3: =PROPER(tbl_Orders[[#This Row],[Status]]) -> Cancelled
A4: 1003 | B4: C003 | C4: P103 | D4: 5 | E4: 45301 | F4: North | G4: 0.15 | H4: Delivered | I4: =PROPER(tbl_Orders[[#This Row],[Region]]) -> North | J4: =PROPER(tbl_Orders[[#This Row],[Status]]) -> Delivered
A5: 1004 | B5: C001 | C5: P104 | D5: 1 | E5: 45303 | F5: East | G5: 0.05 | H5: Delivered | I5: =PROPER(tbl_Orders[[#This Row],[Region]]) -> East | J5: =PROPER(tbl_Orders[[#This Row],[Status]]) -> Delivered
A6: 1005 | B6: C004 | C6: P105 | D6: 3 | E6: 45306 | F6: South | G6: 0 | H6: Delivered | I6: =PROPER(tbl_Orders[[#This Row],[Region]]) -> South | J6: =PROPER(tbl_Orders[[#This Row],[Status]]) -> Delivered
A7: 1006 | B7: C005 | C7: P101 | D7: 10 | E7: 45309 | F7: West | G7: 0.2 | H7: Delivered | I7: =PROPER(tbl_Orders[[#This Row],[Region]]) -> West | J7: =PROPER(tbl_Orders[[#This Row],[Status]]) -> Delivered
A8: 1007 | B8: C002 | C8: P106 | D8: 2 | E8: 45311 | F8: North | G8: 0.1 | H8: Delivered | I8: =PROPER(tbl_Orders[[#This Row],[Region]]) -> North | J8: =PROPER(tbl_Orders[[#This Row],[Status]]) -> Delivered
A9: 1008 | B9: C006 | C9: P107 | D9: 1 | E9: 45313 | F9: East | G9: 0 | H9: Cancelled | I9: =PROPER(tbl_Orders[[#This Row],[Region]]) -> East | J9: =PROPER(tbl_Orders[[#This Row],[Status]]) -> Cancelled
A10: 1009 | B10: C007 | C10: P108 | D10: 4 | E10: 45316 | F10: South | G10: 0.18 | H10: Delivered | I10: =PROPER(tbl_Orders[[#This Row],[Region]]) -> South | J10: =PROPER(tbl_Orders[[#This Row],[Status]]) -> Delivered
A11: 1010 | B11: C003 | C11: P109 | D11: 1 | E11: 45319 | F11: West | G11: 0.08 | H11: Delivered | I11: =PROPER(tbl_Orders[[#This Row],[Region]]) -> West | J11: =PROPER(tbl_Orders[[#This Row],[Status]]) -> Delivered
A12: 1011 | B12: C008 | C12: P110 | D12: 6 | E12: 45321 | F12: North | G12: 0 | H12: Cancelled | I12: =PROPER(tbl_Orders[[#This Row],[Region]]) -> North | J12: =PROPER(tbl_Orders[[#This Row],[Status]]) -> Cancelled
A13: 1012 | B13: C001 | C13: P102 | D13: 2 | E13: 45324 | F13: East | G13: 0.25 | H13: Delivered | I13: =PROPER(tbl_Orders[[#This Row],[Region]]) -> East | J13: =PROPER(tbl_Orders[[#This Row],[Status]]) -> Delivered
... A31: 1030 | B31: C005 | C31: P110 | D31: 5 | E31: 45371 | F31: West | G31: 0.2 | H31: Delivered | I31: =PROPER(tbl_Orders[[#This Row],[Region]]) -> West | J31: =PROPER(tbl_Orders[[#This Row],[Status]]) -> Delivered

Sheet Products
A1: ProductID | B1: ProductName | C1: Category | D1: UnitPrice | E1: Cost | F1: Supplier | G1: ProductMargin
A2: P101 | B2: Wireless Mouse | C2: Electronics | D2: 29.99 | E2: 15 | F2: TechSupplies | G2: 0.4998
A3: P102 | B3: Office Chair | C3: Furniture | D3: 299.99 | E3: 180 | F3: OfficeWorks | G3: 0.4
A4: P103 | B4: Mechanical Keyboard | C4: Electronics | D4: 89.99 | E4: 45 | F4: TechSupplies | G4: 0.5
A5: P104 | B5: Monitor 24" | C5: Electronics | D5: 199.99 | E5: 120 | F5: DisplayCo | G5: 0.4
A6: P105 | B6: Desk Lamp | C6: Home | D6: 39.99 | E6: 18 | F6: HomeGoods | G6: 0.55
A7: P106 | B7: Webcam HD | C7: Electronics | D7: 59.99 | E7: 28 | F7: TechSupplies | G7: 0.53
A8: P107 | B8: Notebook Set | C8: Office Supplies | D8: 24.99 | E8: 10 | F8: PaperCo | G8: 0.6
A9: P108 | B9: Coffee Maker | C9: Home | D9: 79.99 | E9: 40 | F9: HomeGoods | G9: 0.5
A10: P109 | B10: Bluetooth Speaker | C10: Electronics | D10: 49.99 | E10: 25 | F10: AudioTech | G10: 0.5
A11: P110 | B11: File Cabinet | C11: Furniture | D11: 149.99 | E11: 90 | F11: OfficeWorks | G11: 0.4

Sheet Customers
A1: CustomerID | B1: CustomerName | C1: JoinDate | D1: Tier | E1: Email | F1: City | G1: State
A2: C001 | B2: John Smith | C2: 45061 | D2: Gold | E2: john@email.com | F2: New York | G2: NY
A3: C002 | B3: Jane Doe | C3: 45292 | D3: Silver | E3: jane@email.com | F3: Los Angeles | G3: CA
A4: C003 | B4: Robert Johnson | C4: 45160 | D4: Bronze | E4: robert@email.com | F4: Chicago | G4: IL
A5: C004 | B5: Maria Garcia | C5: 45240 | D5: Gold | E5: maria@email.com | F5: Houston | G5: TX
A6: C005 | B6: David Brown | C6: 45336 | D6: Silver | E6: david@email.com | F6: Phoenix | G6: AZ
A7: C006 | B7: Lisa Wilson | C7: 45110 | D7: Bronze | E7: lisa@email.com | F7: Philadelphia | G7: PA
A8: C007 | B8: Michael Lee | C8: 45199 | D8: Gold | E8: michael@email.com | F8: San Antonio | G8: TX
A9: C008 | B9: Sarah Miller | C9: 45352 | D9: Bronze | E9: sarah@email.com | F9: San Diego | G9: CA

Sheet Data_Clean
A1: OrderID | B1: CustomerID | C1: ProductID | D1: Quantity | E1: OrderDate | F1: Region | G1: Discount | H1: Status | I1: CustomerName | J1: CleanName | K1: CustomerTier | L1: CustomerCity | M1: OrderMonth | N1: OrderYear | O1: MonthYear | P1: Quarter | Q1: UnitPrice | R1: Category | S1: DiscountValue | T1: Revenue | U1: OrderSize | V1: Profit
A2: 1001 | B2: C001 | C2: P101 | D2: 2 | E2: 45296 | F2: East | G2: 0.1 | H2: Delivered | I2: =IFERROR(VLOOKUP(tbl_Practice[[#This Row],[CustomerID]],Customers!$A:$G,2,FALSE),"Unknown") -> John Smith | J2: =TRIM(PROPER(tbl_Practice[[#This Row],[CustomerName]])) -> John Smith | K2: =IFERROR(VLOOKUP(tbl_Practice[[#This Row],[CustomerID]],Customers!$A:$G,4,FALSE),"Unknown") -> Gold | L2: =IFERROR(VLOOKUP(tbl_Practice[[#This Row],[CustomerID]],Customers!$A:$G,6,FALSE),"Unknown") -> New York | M2: =TEXT(tbl_Practice[[#This Row],[OrderDate]],"mmmm") -> January | N2: =YEAR(tbl_Practice[[#This Row],[OrderDate]]) -> 2024 | O2: =TEXT(tbl_Practice[[#This Row],[OrderDate]],"mmm-yy") -> Jan-24 | P2: ="Q"&INT((MONTH(tbl_Practice[[#This Row],[OrderDate]])-1)/3)+1&"-"&YEAR(tbl_Practice[[#This Row],[OrderDate]]) -> Q1-2024 | Q2: =IFERROR(VLOOKUP(tbl_Practice[[#This Row],[ProductID]],Products!$A:$G,4,FALSE),0) -> 29.99 | R2: =IFERROR(VLOOKUP(tbl_Practice[[#This Row],[ProductID]],Products!$A:$G,3,FALSE),"Unknown") -> Electronics | S2: =VALUE(SUBSTITUTE(tbl_Practice[[#This Row],[Discount]], "%", "")) -> 0.1 | T2: =tbl_Practice[[#This Row],[Quantity]]*tbl_Practice[[#This Row],[UnitPrice]]*(1-tbl_Practice[[#This Row],[DiscountValue]]) -> 53.982 | U2: =IF(tbl_Practice[[#This Row],[Revenue]]>500,"Large","Standard") -> Standard | V2: =(tbl_Practice[[#This Row],[UnitPrice]]-IFERROR(VLOOKUP(tbl_Practice[[#This Row],[ProductID]],Products!$A:$G,5,FALSE),0))*tbl_Practice[[#This Row],[Quantity]]*(1-tbl_Practice[[#This Row],[DiscountValue]]) -> 26.982
A3: 1002 | B3: C002 | C3: P102 | D3: 1 | E3: 45298 | F3: West | G3: 0 | H3: Cancelled | I3: =IFERROR(VLOOKUP(tbl_Practice[[#This Row],[CustomerID]],Customers!$A:$G,2,FALSE),"Unknown") -> Jane Doe | J3: =TRIM(PROPER(tbl_Practice[[#This Row],[CustomerName]])) -> Jane Doe | K3: =IFERROR(VLOOKUP(tbl_Practice[[#This Row],[CustomerID]],Customers!$A:$G,4,FALSE),"Unknown") -> Silver | L3: =IFERROR(VLOOKUP(tbl_Practice[[#This Row],[CustomerID]],Customers!$A:$G,6,FALSE),"Unknown") -> Los Angeles | M3: =TEXT(tbl_Practice[[#This Row],[OrderDate]],"mmmm") -> January | N3: =YEAR(tbl_Practice[[#This Row],[OrderDate]]) -> 2024 | O3: =TEXT(tbl_Practice[[#This Row],[OrderDate]],"mmm-yy") -> Jan-24 | P3: ="Q"&INT((MONTH(tbl_Practice[[#This Row],[OrderDate]])-1)/3)+1&"-"&YEAR(tbl_Practice[[#This Row],[OrderDate]]) -> Q1-2024 | Q3: =IFERROR(VLOOKUP(tbl_Practice[[#This Row],[ProductID]],Products!$A:$G,4,FALSE),0) -> 299.99 | R3: =IFERROR(VLOOKUP(tbl_Practice[[#This Row],[ProductID]],Products!$A:$G,3,FALSE),"Unknown") -> Furniture | S3: =VALUE(SUBSTITUTE(tbl_Practice[[#This Row],[Discount]], "%", "")) -> 0 | T3: =tbl_Practice[[#This Row],[Quantity]]*tbl_Practice[[#This Row],[UnitPrice]]*(1-tbl_Practice[[#This Row],[DiscountValue]]) -> 299.99 | U3: =IF(tbl_Practice[[#This Row],[Revenue]]>500,"Large","Standard") -> Standard | V3: =(tbl_Practice[[#This Row],[UnitPrice]]-IFERROR(VLOOKUP(tbl_Practice[[#This Row],[ProductID]],Products!$A:$G,5,FALSE),0))*tbl_Practice[[#This Row],[Quantity]]*(1-tbl_Practice[[#This Row],[DiscountValue]]) -> 119.99
A4: 1003 | B4: C003 | C4: P103 | D4: 5 | E4: 45301 | F4: North | G4: 0.15 | H4: Delivered | I4: =IFERROR(VLOOKUP(tbl_Practice[[#This Row],[CustomerID]],Customers!$A:$G,2,FALSE),"Unknown") -> Robert Johnson | J4: =TRIM(PROPER(tbl_Practice[[#This Row],[CustomerName]])) -> Robert Johnson | K4: =IFERROR(VLOOKUP(tbl_Practice[[#This Row],[CustomerID]],Customers!$A:$G,4,FALSE),"Unknown") -> Bronze | L4: =IFERROR(VLOOKUP(tbl_Practice[[#This Row],[CustomerID]],Customers!$A:$G,6,FALSE),"Unknown") -> Chicago | M4: =TEXT(tbl_Practice[[#This Row],[OrderDate]],"mmmm") -> January | N4: =YEAR(tbl_Practice[[#This Row],[OrderDate]]) -> 2024 | O4: =TEXT(tbl_Practice[[#This Row],[OrderDate]],"mmm-yy") -> Jan-24 | P4: ="Q"&INT((MONTH(tbl_Practice[[#This Row],[OrderDate]])-1)/3)+1&"-"&YEAR(tbl_Practice[[#This Row],[OrderDate]]) -> Q1-2024 | Q4: =IFERROR(VLOOKUP(tbl_Practice[[#This Row],[ProductID]],Products!$A:$G,4,FALSE),0) -> 89.99 | R4: =IFERROR(VLOOKUP(tbl_Practice[[#This Row],[ProductID]],Products!$A:$G,3,FALSE),"Unknown") -> Electronics | S4: =VALUE(SUBSTITUTE(tbl_Practice[[#This Row],[Discount]], "%", "")) -> 0.15 | T4: =tbl_Practice[[#This Row],[Quantity]]*tbl_Practice[[#This Row],[UnitPrice]]*(1-tbl_Practice[[#This Row],[DiscountValue]]) -> 382.4575 | U4: =IF(tbl_Practice[[#This Row],[Revenue]]>500,"Large","Standard") -> Standard | V4: =(tbl_Practice[[#This Row],[UnitPrice]]-IFERROR(VLOOKUP(tbl_Practice[[#This Row],[ProductID]],Products!$A:$G,5,FALSE),0))*tbl_Practice[[#This Row],[Quantity]]*(1-tbl_Practice[[#This Row],[DiscountValue]]) -> 191.2075
A5: 1004 | B5: C001 | C5: P104 | D5: 1 | E5: 45303 | F5: East | G5: 0.05 | H5: Delivered | I5: =IFERROR(VLOOKUP(tbl_Practice[[#This Row],[CustomerID]],Customers!$A:$G,2,FALSE),"Unknown") -> John Smith | J5: =TRIM(PROPER(tbl_Practice[[#This Row],[CustomerName]])) -> John Smith | K5: =IFERROR(VLOOKUP(tbl_Practice[[#This Row],[CustomerID]],Customers!$A:$G,4,FALSE),"Unknown") -> Gold | L5: =IFERROR(VLOOKUP(tbl_Practice[[#This Row],[CustomerID]],Customers!$A:$G,6,FALSE),"Unknown") -> New York | M5: =TEXT(tbl_Practice[[#This Row],[OrderDate]],"mmmm") -> January | N5: =YEAR(tbl_Practice[[#This Row],[OrderDate]]) -> 2024 | O5: =TEXT(tbl_Practice[[#This Row],[OrderDate]],"mmm-yy") -> Jan-24 | P5: ="Q"&INT((MONTH(tbl_Practice[[#This Row],[OrderDate]])-1)/3)+1&"-"&YEAR(tbl_Practice[[#This Row],[OrderDate]]) -> Q1-2024 | Q5: =IFERROR(VLOOKUP(tbl_Practice[[#This Row],[ProductID]],Products!$A:$G,4,FALSE),0) -> 199.99 | R5: =IFERROR(VLOOKUP(tbl_Practice[[#This Row],[ProductID]],Products!$A:$G,3,FALSE),"Unknown") -> Electronics | S5: =VALUE(SUBSTITUTE(tbl_Practice[[#This Row],[Discount]], "%", "")) -> 0.05 | T5: =tbl_Practice[[#This Row],[Quantity]]*tbl_Practice[[#This Row],[UnitPrice]]*(1-tbl_Practice[[#This Row],[DiscountValue]]) -> 189.9905 | U5: =IF(tbl_Practice[[#This Row],[Revenue]]>500,"Large","Standard") -> Standard | V5: =(tbl_Practice[[#This Row],[UnitPrice]]-IFERROR(VLOOKUP(tbl_Practice[[#This Row],[ProductID]],Products!$A:$G,5,FALSE),0))*tbl_Practice[[#This Row],[Quantity]]*(1-tbl_Practice[[#This Row],[DiscountValue]]) -> 75.9905
A6: 1005 | B6: C004 | C6: P105 | D6: 3 | E6: 45306 | F6: South | G6: 0 | H6: Delivered | I6: =IFERROR(VLOOKUP(tbl_Practice[[#This Row],[CustomerID]],Customers!$A:$G,2,FALSE),"Unknown") -> Maria Garcia | J6: =TRIM(PROPER(tbl_Practice[[#This Row],[CustomerName]])) -> Maria Garcia | K6: =IFERROR(VLOOKUP(tbl_Practice[[#This Row],[CustomerID]],Customers!$A:$G,4,FALSE),"Unknown") -> Gold | L6: =IFERROR(VLOOKUP(tbl_Practice[[#This Row],[CustomerID]],Customers!$A:$G,6,FALSE),"Unknown") -> Houston | M6: =TEXT(tbl_Practice[[#This Row],[OrderDate]],"mmmm") -> January | N6: =YEAR(tbl_Practice[[#This Row],[OrderDate]]) -> 2024 | O6: =TEXT(tbl_Practice[[#This Row],[OrderDate]],"mmm-yy") -> Jan-24 | P6: ="Q"&INT((MONTH(tbl_Practice[[#This Row],[OrderDate]])-1)/3)+1&"-"&YEAR(tbl_Practice[[#This Row],[OrderDate]]) -> Q1-2024 | Q6: =IFERROR(VLOOKUP(tbl_Practice[[#This Row],[ProductID]],Products!$A:$G,4,FALSE),0) -> 39.99 | R6: =IFERROR(VLOOKUP(tbl_Practice[[#This Row],[ProductID]],Products!$A:$G,3,FALSE),"Unknown") -> Home | S6: =VALUE(SUBSTITUTE(tbl_Practice[[#This Row],[Discount]], "%", "")) -> 0 | T6: =tbl_Practice[[#This Row],[Quantity]]*tbl_Practice[[#This Row],[UnitPrice]]*(1-tbl_Practice[[#This Row],[DiscountValue]]) -> 119.97 | U6: =IF(tbl_Practice[[#This Row],[Revenue]]>500,"Large","Standard") -> Standard | V6: =(tbl_Practice[[#This Row],[UnitPrice]]-IFERROR(VLOOKUP(tbl_Practice[[#This Row],[ProductID]],Products!$A:$G,5,FALSE),0))*tbl_Practice[[#This Row],[Quantity]]*(1-tbl_Practice[[#This Row],[DiscountValue]]) -> 65.97
A7: 1006 | B7: C005 | C7: P101 | D7: 10 | E7: 45309 | F7: West | G7: 0.2 | H7: Delivered | I7: =IFERROR(VLOOKUP(tbl_Practice[[#This Row],[CustomerID]],Customers!$A:$G,2,FALSE),"Unknown") -> David Brown | J7: =TRIM(PROPER(tbl_Practice[[#This Row],[CustomerName]])) -> David Brown | K7: =IFERROR(VLOOKUP(tbl_Practice[[#This Row],[CustomerID]],Customers!$A:$G,4,FALSE),"Unknown") -> Silver | L7: =IFERROR(VLOOKUP(tbl_Practice[[#This Row],[CustomerID]],Customers!$A:$G,6,FALSE),"Unknown") -> Phoenix | M7: =TEXT(tbl_Practice[[#This Row],[OrderDate]],"mmmm") -> January | N7: =YEAR(tbl_Practice[[#This Row],[OrderDate]]) -> 2024 | O7: =TEXT(tbl_Practice[[#This Row],[OrderDate]],"mmm-yy") -> Jan-24 | P7: ="Q"&INT((MONTH(tbl_Practice[[#This Row],[OrderDate]])-1)/3)+1&"-"&YEAR(tbl_Practice[[#This Row],[OrderDate]]) -> Q1-2024 | Q7: =IFERROR(VLOOKUP(tbl_Practice[[#This Row],[ProductID]],Products!$A:$G,4,FALSE),0) -> 29.99 | R7: =IFERROR(VLOOKUP(tbl_Practice[[#This Row],[ProductID]],Products!$A:$G,3,FALSE),"Unknown") -> Electronics | S7: =VALUE(SUBSTITUTE(tbl_Practice[[#This Row],[Discount]], "%", "")) -> 0.2 | T7: =tbl_Practice[[#This Row],[Quantity]]*tbl_Practice[[#This Row],[UnitPrice]]*(1-tbl_Practice[[#This Row],[DiscountValue]]) -> 239.92 | U7: =IF(tbl_Practice[[#This Row],[Revenue]]>500,"Large","Standard") -> Standard | V7: =(tbl_Practice[[#This Row],[UnitPrice]]-IFERROR(VLOOKUP(tbl_Practice[[#This Row],[ProductID]],Products!$A:$G,5,FALSE),0))*tbl_Practice[[#This Row],[Quantity]]*(1-tbl_Practice[[#This Row],[DiscountValue]]) -> 119.92
A8: 1007 | B8: C002 | C8: P106 | D8: 2 | E8: 45311 | F8: North | G8: 0.1 | H8: Delivered | I8: =IFERROR(VLOOKUP(tbl_Practice[[#This Row],[CustomerID]],Customers!$A:$G,2,FALSE),"Unknown") -> Jane Doe | J8: =TRIM(PROPER(tbl_Practice[[#This Row],[CustomerName]])) -> Jane Doe | K8: =IFERROR(VLOOKUP(tbl_Practice[[#This Row],[CustomerID]],Customers!$A:$G,4,FALSE),"Unknown") -> Silver | L8: =IFERROR(VLOOKUP(tbl_Practice[[#This Row],[CustomerID]],Customers!$A:$G,6,FALSE),"Unknown") -> Los Angeles | M8: =TEXT(tbl_Practice[[#This Row],[OrderDate]],"mmmm") -> January | N8: =YEAR(tbl_Practice[[#This Row],[OrderDate]]) -> 2024 | O8: =TEXT(tbl_Practice[[#This Row],[OrderDate]],"mmm-yy") -> Jan-24 | P8: ="Q"&INT((MONTH(tbl_Practice[[#This Row],[OrderDate]])-1)/3)+1&"-"&YEAR(tbl_Practice[[#This Row],[OrderDate]]) -> Q1-2024 | Q8: =IFERROR(VLOOKUP(tbl_Practice[[#This Row],[ProductID]],Products!$A:$G,4,FALSE),0) -> 59.99 | R8: =IFERROR(VLOOKUP(tbl_Practice[[#This Row],[ProductID]],Products!$A:$G,3,FALSE),"Unknown") -> Electronics | S8: =VALUE(SUBSTITUTE(tbl_Practice[[#This Row],[Discount]], "%", "")) -> 0.1 | T8: =tbl_Practice[[#This Row],[Quantity]]*tbl_Practice[[#This Row],[UnitPrice]]*(1-tbl_Practice[[#This Row],[DiscountValue]]) -> 107.982 | U8: =IF(tbl_Practice[[#This Row],[Revenue]]>500,"Large","Standard") -> Standard | V8: =(tbl_Practice[[#This Row],[UnitPrice]]-IFERROR(VLOOKUP(tbl_Practice[[#This Row],[ProductID]],Products!$A:$G,5,FALSE),0))*tbl_Practice[[#This Row],[Quantity]]*(1-tbl_Practice[[#This Row],[DiscountValue]]) -> 57.582
A9: 1008 | B9: C006 | C9: P107 | D9: 1 | E9: 45313 | F9: East | G9: 0 | H9: Cancelled | I9: =IFERROR(VLOOKUP(tbl_Practice[[#This Row],[CustomerID]],Customers!$A:$G,2,FALSE),"Unknown") -> Lisa Wilson | J9: =TRIM(PROPER(tbl_Practice[[#This Row],[CustomerName]])) -> Lisa Wilson | K9: =IFERROR(VLOOKUP(tbl_Practice[[#This Row],[CustomerID]],Customers!$A:$G,4,FALSE),"Unknown") -> Bronze | L9: =IFERROR(VLOOKUP(tbl_Practice[[#This Row],[CustomerID]],Customers!$A:$G,6,FALSE),"Unknown") -> Philadelphia | M9: =TEXT(tbl_Practice[[#This Row],[OrderDate]],"mmmm") -> January | N9: =YEAR(tbl_Practice[[#This Row],[OrderDate]]) -> 2024 | O9: =TEXT(tbl_Practice[[#This Row],[OrderDate]],"mmm-yy") -> Jan-24 | P9: ="Q"&INT((MONTH(tbl_Practice[[#This Row],[OrderDate]])-1)/3)+1&"-"&YEAR(tbl_Practice[[#This Row],[OrderDate]]) -> Q1-2024 | Q9: =IFERROR(VLOOKUP(tbl_Practice[[#This Row],[ProductID]],Products!$A:$G,4,FALSE),0) -> 24.99 | R9: =IFERROR(VLOOKUP(tbl_Practice[[#This Row],[ProductID]],Products!$A:$G,3,FALSE),"Unknown") -> Office Supplies | S9: =VALUE(SUBSTITUTE(tbl_Practice[[#This Row],[Discount]], "%", "")) -> 0 | T9: =tbl_Practice[[#This Row],[Quantity]]*tbl_Practice[[#This Row],[UnitPrice]]*(1-tbl_Practice[[#This Row],[DiscountValue]]) -> 24.99 | U9: =IF(tbl_Practice[[#This Row],[Revenue]]>500,"Large","Standard") -> Standard | V9: =(tbl_Practice[[#This Row],[UnitPrice]]-IFERROR(VLOOKUP(tbl_Practice[[#This Row],[ProductID]],Products!$A:$G,5,FALSE),0))*tbl_Practice[[#This Row],[Quantity]]*(1-tbl_Practice[[#This Row],[DiscountValue]]) -> 14.99
A10: 1009 | B10: C007 | C10: P108 | D10: 4 | E10: 45316 | F10: South | G10: 0.18 | H10: Delivered | I10: =IFERROR(VLOOKUP(tbl_Practice[[#This Row],[CustomerID]],Customers!$A:$G,2,FALSE),"Unknown") -> Michael Lee | J10: =TRIM(PROPER(tbl_Practice[[#This Row],[CustomerName]])) -> Michael Lee | K10: =IFERROR(VLOOKUP(tbl_Practice[[#This Row],[CustomerID]],Customers!$A:$G,4,FALSE),"Unknown") -> Gold | L10: =IFERROR(VLOOKUP(tbl_Practice[[#This Row],[CustomerID]],Customers!$A:$G,6,FALSE),"Unknown") -> San Antonio | M10: =TEXT(tbl_Practice[[#This Row],[OrderDate]],"mmmm") -> January | N10: =YEAR(tbl_Practice[[#This Row],[OrderDate]]) -> 2024 | O10: =TEXT(tbl_Practice[[#This Row],[OrderDate]],"mmm-yy") -> Jan-24 | P10: ="Q"&INT((MONTH(tbl_Practice[[#This Row],[OrderDate]])-1)/3)+1&"-"&YEAR(tbl_Practice[[#This Row],[OrderDate]]) -> Q1-2024 | Q10: =IFERROR(VLOOKUP(tbl_Practice[[#This Row],[ProductID]],Products!$A:$G,4,FALSE),0) -> 79.99 | R10: =IFERROR(VLOOKUP(tbl_Practice[[#This Row],[ProductID]],Products!$A:$G,3,FALSE),"Unknown") -> Home | S10: =VALUE(SUBSTITUTE(tbl_Practice[[#This Row],[Discount]], "%", "")) -> 0.18 | T10: =tbl_Practice[[#This Row],[Quantity]]*tbl_Practice[[#This Row],[UnitPrice]]*(1-tbl_Practice[[#This Row],[DiscountValue]]) -> 262.3672 | U10: =IF(tbl_Practice[[#This Row],[Revenue]]>500,"Large","Standard") -> Standard | V10: =(tbl_Practice[[#This Row],[UnitPrice]]-IFERROR(VLOOKUP(tbl_Practice[[#This Row],[ProductID]],Products!$A:$G,5,FALSE),0))*tbl_Practice[[#This Row],[Quantity]]*(1-tbl_Practice[[#This Row],[DiscountValue]]) -> 131.1672
A11: 1010 | B11: C003 | C11: P109 | D11: 1 | E11: 45319 | F11: West | G11: 0.08 | H11: Delivered | I11: =IFERROR(VLOOKUP(tbl_Practice[[#This Row],[CustomerID]],Customers!$A:$G,2,FALSE),"Unknown") -> Robert Johnson | J11: =TRIM(PROPER(tbl_Practice[[#This Row],[CustomerName]])) -> Robert Johnson | K11: =IFERROR(VLOOKUP(tbl_Practice[[#This Row],[CustomerID]],Customers!$A:$G,4,FALSE),"Unknown") -> Bronze | L11: =IFERROR(VLOOKUP(tbl_Practice[[#This Row],[CustomerID]],Customers!$A:$G,6,FALSE),"Unknown") -> Chicago | M11: =TEXT(tbl_Practice[[#This Row],[OrderDate]],"mmmm") -> January | N11: =YEAR(tbl_Practice[[#This Row],[OrderDate]]) -> 2024 | O11: =TEXT(tbl_Practice[[#This Row],[OrderDate]],"mmm-yy") -> Jan-24 | P11: ="Q"&INT((MONTH(tbl_Practice[[#This Row],[OrderDate]])-1)/3)+1&"-"&YEAR(tbl_Practice[[#This Row],[OrderDate]]) -> Q1-2024 | Q11: =IFERROR(VLOOKUP(tbl_Practice[[#This Row],[ProductID]],Products!$A:$G,4,FALSE),0) -> 49.99 | R11: =IFERROR(VLOOKUP(tbl_Practice[[#This Row],[ProductID]],Products!$A:$G,3,FALSE),"Unknown") -> Electronics | S11: =VALUE(SUBSTITUTE(tbl_Practice[[#This Row],[Discount]], "%", "")) -> 0.08 | T11: =tbl_Practice[[#This Row],[Quantity]]*tbl_Practice[[#This Row],[UnitPrice]]*(1-tbl_Practice[[#This Row],[DiscountValue]]) -> 45.9908 | U11: =IF(tbl_Practice[[#This Row],[Revenue]]>500,"Large","Standard") -> Standard | V11: =(tbl_Practice[[#This Row],[UnitPrice]]-IFERROR(VLOOKUP(tbl_Practice[[#This Row],[ProductID]],Products!$A:$G,5,FALSE),0))*tbl_Practice[[#This Row],[Quantity]]*(1-tbl_Practice[[#This Row],[DiscountValue]]) -> 22.9908
A12: 1011 | B12: C008 | C12: P110 | D12: 6 | E12: 45321 | F12: North | G12: 0 | H12: Cancelled | I12: =IFERROR(VLOOKUP(tbl_Practice[[#This Row],[CustomerID]],Customers!$A:$G,2,FALSE),"Unknown") -> Sarah Miller | J12: =TRIM(PROPER(tbl_Practice[[#This Row],[CustomerName]])) -> Sarah Miller | K12: =IFERROR(VLOOKUP(tbl_Practice[[#This Row],[CustomerID]],Customers!$A:$G,4,FALSE),"Unknown") -> Bronze | L12: =IFERROR(VLOOKUP(tbl_Practice[[#This Row],[CustomerID]],Customers!$A:$G,6,FALSE),"Unknown") -> San Diego | M12: =TEXT(tbl_Practice[[#This Row],[OrderDate]],"mmmm") -> January | N12: =YEAR(tbl_Practice[[#This Row],[OrderDate]]) -> 2024 | O12: =TEXT(tbl_Practice[[#This Row],[OrderDate]],"mmm-yy") -> Jan-24 | P12: ="Q"&INT((MONTH(tbl_Practice[[#This Row],[OrderDate]])-1)/3)+1&"-"&YEAR(tbl_Practice[[#This Row],[OrderDate]]) -> Q1-2024 | Q12: =IFERROR(VLOOKUP(tbl_Practice[[#This Row],[ProductID]],Products!$A:$G,4,FALSE),0) -> 149.99 | R12: =IFERROR(VLOOKUP(tbl_Practice[[#This Row],[ProductID]],Products!$A:$G,3,FALSE),"Unknown") -> Furniture | S12: =VALUE(SUBSTITUTE(tbl_Practice[[#This Row],[Discount]], "%", "")) -> 0 | T12: =tbl_Practice[[#This Row],[Quantity]]*tbl_Practice[[#This Row],[UnitPrice]]*(1-tbl_Practice[[#This Row],[DiscountValue]]) -> 899.94 | U12: =IF(tbl_Practice[[#This Row],[Revenue]]>500,"Large","Standard") -> Large | V12: =(tbl_Practice[[#This Row],[UnitPrice]]-IFERROR(VLOOKUP(tbl_Practice[[#This Row],[ProductID]],Products!$A:$G,5,FALSE),0))*tbl_Practice[[#This Row],[Quantity]]*(1-tbl_Practice[[#This Row],[DiscountValue]]) -> 359.94
A13: 1012 | B13: C001 | C13: P102 | D13: 2 | E13: 45324 | F13: East | G13: 0.25 | H13: Delivered | I13: =IFERROR(VLOOKUP(tbl_Practice[[#This Row],[CustomerID]],Customers!$A:$G,2,FALSE),"Unknown") -> John Smith | J13: =TRIM(PROPER(tbl_Practice[[#This Row],[CustomerName]])) -> John Smith | K13: =IFERROR(VLOOKUP(tbl_Practice[[#This Row],[CustomerID]],Customers!$A:$G,4,FALSE),"Unknown") -> Gold | L13: =IFERROR(VLOOKUP(tbl_Practice[[#This Row],[CustomerID]],Customers!$A:$G,6,FALSE),"Unknown") -> New York | M13: =TEXT(tbl_Practice[[#This Row],[OrderDate]],"mmmm") -> February | N13: =YEAR(tbl_Practice[[#This Row],[OrderDate]]) -> 2024 | O13: =TEXT(tbl_Practice[[#This Row],[OrderDate]],"mmm-yy") -> Feb-24 | P13: ="Q"&INT((MONTH(tbl_Practice[[#This Row],[OrderDate]])-1)/3)+1&"-"&YEAR(tbl_Practice[[#This Row],[OrderDate]]) -> Q1-2024 | Q13: =IFERROR(VLOOKUP(tbl_Practice[[#This Row],[ProductID]],Products!$A:$G,4,FALSE),0) -> 299.99 | R13: =IFERROR(VLOOKUP(tbl_Practice[[#This Row],[ProductID]],Products!$A:$G,3,FALSE),"Unknown") -> Furniture | S13: =VALUE(SUBSTITUTE(tbl_Practice[[#This Row],[Discount]], "%", "")) -> 0.25 | T13: =tbl_Practice[[#This Row],[Quantity]]*tbl_Practice[[#This Row],[UnitPrice]]*(1-tbl_Practice[[#This Row],[DiscountValue]]) -> 449.985 | U13: =IF(tbl_Practice[[#This Row],[Revenue]]>500,"Large","Standard") -> Standard | V13: =(tbl_Practice[[#This Row],[UnitPrice]]-IFERROR(VLOOKUP(tbl_Practice[[#This Row],[ProductID]],Products!$A:$G,5,FALSE),0))*tbl_Practice[[#This Row],[Quantity]]*(1-tbl_Practice[[#This Row],[DiscountValue]]) -> 179.985
... A31: 1030 | B31: C005 | C31: P110 | D31: 5 | E31: 45371 | F31: west | G31: 0.2 | H31: Delivered | I31: =IFERROR(VLOOKUP(tbl_Practice[[#This Row],[CustomerID]],Customers!$A:$G,2,FALSE),"Unknown") -> David Brown | J31: =TRIM(PROPER(tbl_Practice[[#This Row],[CustomerName]])) -> David Brown | K31: =IFERROR(VLOOKUP(tbl_Practice[[#This Row],[CustomerID]],Customers!$A:$G,4,FALSE),"Unknown") -> Silver | L31: =IFERROR(VLOOKUP(tbl_Practice[[#This Row],[CustomerID]],Customers!$A:$G,6,FALSE),"Unknown") -> Phoenix | M31: =TEXT(tbl_Practice[[#This Row],[OrderDate]],"mmmm") -> March | N31: =YEAR(tbl_Practice[[#This Row],[OrderDate]]) -> 2024 | O31: =TEXT(tbl_Practice[[#This Row],[OrderDate]],"mmm-yy") -> Mar-24 | P31: ="Q"&INT((MONTH(tbl_Practice[[#This Row],[OrderDate]])-1)/3)+1&"-"&YEAR(tbl_Practice[[#This Row],[OrderDate]]) -> Q1-2024 | Q31: =IFERROR(VLOOKUP(tbl_Practice[[#This Row],[ProductID]],Products!$A:$G,4,FALSE),0) -> 149.99 | R31: =IFERROR(VLOOKUP(tbl_Practice[[#This Row],[ProductID]],Products!$A:$G,3,FALSE),"Unknown") -> Furniture | S31: =VALUE(SUBSTITUTE(tbl_Practice[[#This Row],[Discount]], "%", "")) -> 0.2 | T31: =tbl_Practice[[#This Row],[Quantity]]*tbl_Practice[[#This Row],[UnitPrice]]*(1-tbl_Practice[[#This Row],[DiscountValue]]) -> 599.96 | U31: =IF(tbl_Practice[[#This Row],[Revenue]]>500,"Large","Standard") -> Large | V31: =(tbl_Practice[[#This Row],[UnitPrice]]-IFERROR(VLOOKUP(tbl_Practice[[#This Row],[ProductID]],Products!$A:$G,5,FALSE),0))*tbl_Practice[[#This Row],[Quantity]]*(1-tbl_Practice[[#This Row],[DiscountValue]]) -> 239.96

Sheet Analysis
A1: Metric | B1: Results
A2: Total Revenue(Delivered,East) | B2: =SUMIFS(Data_Clean!T:T,Data_Clean!H:H,"Delivered",Data_Clean!F:F,"East") -> 996.922
A3: Count of large Orders(Silver Tier) | B3: =COUNTIFS(Data_Clean!U:U,"Large",Data_Clean!K:K,"Silver") -> 3
A4: Avg.Discount(Furniture Category) | B4: =AVERAGEIFS(Data_Clean!S:S,Data_Clean!R:R,"Furniture") -> 0.091666667

Sheet Dashboard
C1: Sales Performance Dashboard
A3: Key Metrics
B4: =Analysis!B2 -> 996.922
B5: =Analysis!B3 -> 3
B6: =Analysis!B4 -> 0.091666667
A9: Monthly Sales Trend
A10: Row Labels | B10: Sum of Revenue
A11: Feb-24 | B11: 3643.1578
A12: Jan-24 | B12: 2627.58
A13: Mar-24 | B13: 1953.9838
A14: Grand Total | B14: 8224.7216
D18: Top 5 customers
A20: Revenue by Category | D20: Customer | E20: Total Revenue
A21: Row Labels | B21: Sum of Revenue | D21: Sarah Miller | E21: 1355.879
A22: Electronics | B22: 3871.328 | D22: Maria Garcia | E22: 704.3455
A23: Furniture | B23: 2939.847 | D23: Lisa Wilson | E23: 705.9381
A24: Home | B24: 1316.5854 | D24: John Smith | E24: 1138.3107
A25: Office Supplies | B25: 96.9612 | D25: David Brown | E25: 2639.799
A26: Grand Total | B26: 8224.7216 | D26: Grand Total | E26: 6544.2723

Sheet _README
A1: Sales Performance Analysis Dashboard
D2: Navigation
A3: Project Overview | D3: Overview
D4: Data Dictionary
A5: Objective:To analyse Q1 2024 Sales data,identify the key performance trends and build an attractive dashboard for business decision-making. | D5: Sheets
A6: Scope:Analysis of 30+ sales orders across 8 customers and 10 product categories | D6: How to Use
A7: Tools Used:Microsoft Excel 2013(Advanced Formulas,PivotTables,Charts,Slicers)
A8: Key Achievements:
A9: .Automated data cleaning and enrichment using 15+ Excel functions
A10: .Built dynamic,interactive dasboard with one-click filtering.
A11: .Identified top-performing regions,products and customer segments.
A14: Data Dictionary
A15: Table Name | B15: Column | C15: Description | D15: Sample Value
A16: tbl_Practice | B16: OrderID | C16: Unique Order Identifier | D16: 1001
A17: tbl_Practice | B17: Revenue | C17: Calculated:Quantity*UnitPrice*(1-Discount) | D17: 53.98
A18: tbl_Practice | B18: OrderSize | C18: Categorized:"Large"ifRevenue>$500 | D18: Standard
A19: tbl_Products | B19: Category | C19: Product category group | D19: Electronics
A20: tbl_Customers | B20: Tier | C20: Customer loyalty level
A22: Workbook Structure
A23: SHEET GUIDE:
A24: _README(This Sheet):Documentation
A25: Data_Clean:Master analysis table(tbl_Practice) with all calculated columns
A26: Analysis:Key metrics calculated using SUMIFS,COUNTIFS,AVERAGEIFS
A27: Dashboard:Interactive report with charts and slicers
A28: Products:Reference table for product details
A29: Customers:Reference table for customer information
A30: How to use This Dashboard
A31: INTERACTIVE FEATURES:
A32: 1.Slicers(Right side):Click any Region,Category or customerTier to filter all charts
A33: 2.Charts Update:Line chart and category chart update instantly with slicer selections
... A40: All Pivot Tables,vharts and metrics update automatically

Sheet Error Check
A1: Data Quality Check
A3: Missing Customer IDs | B3: =COUNTIF(Data_Clean!B:B,"C???"-COUNTA(Customers!A:A)) -> 0
A4: Missing Product IDs | B4: =COUNTIF(Data_Clean!C:C,"P???")-COUNTA(Products!A:A) -> 19
A5: Invalid Regions | B5: =COUNTIF(Orders!F:F,"<>North")+COUNTIF(Orders!F:F,"<>South"+COUNTIF(Orders!F:F,"<>East"+COUNTIF(Orders!F:F,"<>West")-COUNTA(Orders!F:F))) -> 1048569
A6: Case Issues Fixed | B6: =COUNTIF(Orders!F:F,"west"+COUNTIF(Orders!H:H,"Delivered")) -> 0
